siedle/__init__.py
ha_siedle_python-0.0.2.dist-info/LICENSE
ha_siedle_python-0.0.2.dist-info/METADATA
ha_siedle_python-0.0.2.dist-info/WHEEL
ha_siedle_python-0.0.2.dist-info/entry_points.txt
ha_siedle_python-0.0.2.dist-info/top_level.txt
ha_siedle_python-0.0.2.dist-info/RECORD
