Metadata-Version: 2.1
Name: ha-siedle-python
Version: 0.0.2
Summary: Python library for interfacing with Siedle IQ devices.
Home-page: https://github.com/Kannix2005/ha_siedle_python
Author: Stefan Altheimer
Author-email: me@stefan-altheimer.de
License: UNKNOWN
Keywords: siedle sip doorbell door bell iq
Platform: UNKNOWN
Classifier: Development Status :: 3 - Alpha
Classifier: Intended Audience :: Developers
Classifier: Topic :: Software Development :: Build Tools
Classifier: License :: OSI Approved :: MIT License
Classifier: Programming Language :: Python :: 3
Classifier: Programming Language :: Python :: 3.4
Classifier: Programming Language :: Python :: 3.5
Classifier: Programming Language :: Python :: 3.6
License-File: LICENSE
